peewee-stubs/METADATA.toml
peewee-stubs/__init__.pyi
peewee-stubs/py.typed
playhouse-stubs/METADATA.toml
playhouse-stubs/__init__.pyi
playhouse-stubs/flask_utils.pyi
playhouse-stubs/py.typed
types_peewee-3.19.0.20260109.dist-info/licenses/LICENSE
types_peewee-3.19.0.20260109.dist-info/METADATA
types_peewee-3.19.0.20260109.dist-info/WHEEL
types_peewee-3.19.0.20260109.dist-info/top_level.txt
types_peewee-3.19.0.20260109.dist-info/RECORD
